README.md
setup.py
schapi/__init__.py
schapi/api.py
schapi/datastructure.py
schapi.egg-info/PKG-INFO
schapi.egg-info/SOURCES.txt
schapi.egg-info/dependency_links.txt
schapi.egg-info/requires.txt
schapi.egg-info/top_level.txt