Metadata-Version: 1.1
Name: schapi
Version: 1.2
Summary: Korean School meal API
Home-page: https://github.com/DSM-SchoolAPI/schapi-py
Author: PlanB
Author-email: mingyu.planb@gmail.com
License: Apache License 2.0
Platform: UNKNOWN
Classifier: Programming Language :: Python
Classifier: Programming Language :: Python :: 3
Classifier: Topic :: Software Development :: Libraries :: Python Modules
